AUTHORS.rst
CONTRIBUTING.rst
HISTORY.rst
LICENSE
MANIFEST.in
Makefile
README.rst
TODO.rst
VERSION
pytest.ini
requirements-dev.txt
requirements-install.txt
requirements-setup.txt
requirements-tests.txt
setup.cfg
setup.py
tox.ini
docs/Makefile
docs/authors.rst
docs/conf.py
docs/contributing.rst
docs/history.rst
docs/index.rst
docs/installation.rst
docs/make.bat
docs/modules.rst
docs/readme.rst
docs/requirements.txt
docs/scrapy_redis.rst
example-project/Dockerfile
example-project/README.rst
example-project/docker-compose.yml
example-project/process_items.py
example-project/requirements.txt
example-project/scrapy.cfg
example-project/example/__init__.py
example-project/example/items.py
example-project/example/pipelines.py
example-project/example/settings.py
example-project/example/spiders/__init__.py
example-project/example/spiders/dmoz.py
example-project/example/spiders/mycrawler_redis.py
example-project/example/spiders/myspider_redis.py
src/scrapy_redis/__init__.py
src/scrapy_redis/connection.py
src/scrapy_redis/defaults.py
src/scrapy_redis/dupefilter.py
src/scrapy_redis/picklecompat.py
src/scrapy_redis/pipelines.py
src/scrapy_redis/queue.py
src/scrapy_redis/scheduler.py
src/scrapy_redis/spiders.py
src/scrapy_redis/stats.py
src/scrapy_redis/utils.py
src/scrapyer_redis.egg-info/PKG-INFO
src/scrapyer_redis.egg-info/SOURCES.txt
src/scrapyer_redis.egg-info/dependency_links.txt
src/scrapyer_redis.egg-info/requires.txt
src/scrapyer_redis.egg-info/top_level.txt
tests/test_connection.py
tests/test_dupefilter.py
tests/test_package_import.py
tests/test_picklecompat.py
tests/test_queue.py
tests/test_scrapy_redis.py
tests/test_spiders.py
tests/test_utils.py